[
  {
    "workflow": "n8n workflow",
    "platform": "GoogleTrends",
    "country": "US",
    "popularity_metrics": {
      "trend_values": [
        10,
        9,
        10,
        12,
        13,
        11,
        10,
        9,
        10,
        15
      ],
      "start_value": 52,
      "end_value": 15,
      "trend_percentage_change": -71.15
    }
  },
  {
    "workflow": "n8n airtable",
    "platform": "GoogleTrends",
    "country": "IN",
    "popularity_metrics": {
      "trend_values": [
        0,
        0,
        0,
        0,
        0,
        0,
        0,
        0,
        0,
        0
      ],
      "start_value": 0,
      "end_value": 0,
      "trend_percentage_change": 0
    }
  }
]