[
  {
    "workflow": "Build Agents INSTANTLY with n8n's Native Text to Workflow Builder #n8n #artificialintelligence",
    "platform": "YouTube",
    "source_id": "rXpHzWXjHrw",
    "url": "https://www.youtube.com/watch?v=rXpHzWXjHrw",
    "country": "US",
    "popularity_metrics": {
      "views": 26859,
      "likes": 1266,
      "comments": 29,
      "like_to_view_ratio": 0.047135,
      "comment_to_view_ratio": 0.00108
    }
  },
  {
    "workflow": "The Only 12 n8n AI Automations You'll Ever Need (Steal These)",
    "platform": "YouTube",
    "source_id": "niHtZBNaJ58",
    "url": "https://www.youtube.com/watch?v=niHtZBNaJ58",
    "country": "US",
    "popularity_metrics": {
      "views": 171544,
      "likes": 6942,
      "comments": 60,
      "like_to_view_ratio": 0.040468,
      "comment_to_view_ratio": 0.00035
    }
  },
  {
    "workflow": "n8n Course for Beginners – Build Complex Workflows & Master AI Integration",
    "platform": "YouTube",
    "source_id": "GIZzRGYpCbM",
    "url": "https://www.youtube.com/watch?v=GIZzRGYpCbM",
    "country": "US",
    "popularity_metrics": {
      "views": 107679,
      "likes": 3278,
      "comments": 95,
      "like_to_view_ratio": 0.030442,
      "comment_to_view_ratio": 0.000882
    }
  },
  {
    "workflow": "2000+ Free n8n Workflows on GitHub  👨‍💻 | Boost Your Productivity Instantly! #shorts",
    "platform": "YouTube",
    "source_id": "g2I5SaGTn4w",
    "url": "https://www.youtube.com/watch?v=g2I5SaGTn4w",
    "country": "US",
    "popularity_metrics": {
      "views": 334039,
      "likes": 7440,
      "comments": 6175,
      "like_to_view_ratio": 0.022273,
      "comment_to_view_ratio": 0.018486
    }
  },
  {
    "workflow": "10 n8n Workflows to Automate Your Entire Business!",
    "platform": "YouTube",
    "source_id": "PhVTDydFGo0",
    "url": "https://www.youtube.com/watch?v=PhVTDydFGo0",
    "country": "US",
    "popularity_metrics": {
      "views": 18622,
      "likes": 290,
      "comments": 175,
      "like_to_view_ratio": 0.015573,
      "comment_to_view_ratio": 0.009397
    }
  },
  {
    "workflow": "Seriously, please watch this before you start learning n8n",
    "platform": "YouTube",
    "source_id": "ofC4OeNjDx8",
    "url": "https://www.youtube.com/watch?v=ofC4OeNjDx8",
    "country": "US",
    "popularity_metrics": {
      "views": 136618,
      "likes": 3444,
      "comments": 472,
      "like_to_view_ratio": 0.025209,
      "comment_to_view_ratio": 0.003455
    }
  },
  {
    "workflow": "n8n Quick Start Tutorial: Build Your First Workflow [2025]",
    "platform": "YouTube",
    "source_id": "4cQWJViybAQ",
    "url": "https://www.youtube.com/watch?v=4cQWJViybAQ",
    "country": "US",
    "popularity_metrics": {
      "views": 742391,
      "likes": 8492,
      "comments": 211,
      "like_to_view_ratio": 0.011439,
      "comment_to_view_ratio": 0.000284
    }
  },
  {
    "workflow": "n8n Tutorial for Beginners: How to Build AI Automations for FREE (Step-by-Step)",
    "platform": "YouTube",
    "source_id": "Fy1UCBcgF2o",
    "url": "https://www.youtube.com/watch?v=Fy1UCBcgF2o",
    "country": "US",
    "popularity_metrics": {
      "views": 489880,
      "likes": 8768,
      "comments": 207,
      "like_to_view_ratio": 0.017898,
      "comment_to_view_ratio": 0.000423
    }
  },
  {
    "workflow": "n8n Tutorial for Beginners 2026: How to Build AI Agents",
    "platform": "YouTube",
    "source_id": "TKnaDGpN7Ns",
    "url": "https://www.youtube.com/watch?v=TKnaDGpN7Ns",
    "country": "US",
    "popularity_metrics": {
      "views": 36007,
      "likes": 0,
      "comments": 19,
      "like_to_view_ratio": 0.0,
      "comment_to_view_ratio": 0.000528
    }
  },
  {
    "workflow": "Build a Whatsapp AI Agent for appointment handling (n8n Tutorial) #n8n #aiautomation",
    "platform": "YouTube",
    "source_id": "vcvRVlc_VFg",
    "url": "https://www.youtube.com/watch?v=vcvRVlc_VFg",
    "country": "US",
    "popularity_metrics": {
      "views": 816297,
      "likes": 21276,
      "comments": 584,
      "like_to_view_ratio": 0.026064,
      "comment_to_view_ratio": 0.000715
    }
  },
  {
    "workflow": "I Built the Ultimate Team of Agents in n8n  #artificialintelligence #n8n #agentgpt  #techtok #coding",
    "platform": "YouTube",
    "source_id": "2aC2ly7vKtM",
    "url": "https://www.youtube.com/watch?v=2aC2ly7vKtM",
    "country": "US",
    "popularity_metrics": {
      "views": 991797,
      "likes": 38714,
      "comments": 411,
      "like_to_view_ratio": 0.039034,
      "comment_to_view_ratio": 0.000414
    }
  },
  {
    "workflow": "I'll never use n8n the same......",
    "platform": "YouTube",
    "source_id": "s96JeuuwLzc",
    "url": "https://www.youtube.com/watch?v=s96JeuuwLzc",
    "country": "US",
    "popularity_metrics": {
      "views": 367169,
      "likes": 12583,
      "comments": 1241,
      "like_to_view_ratio": 0.03427,
      "comment_to_view_ratio": 0.00338
    }
  },
  {
    "workflow": "Master 80% of n8n in 36 Minutes",
    "platform": "YouTube",
    "source_id": "e3OV3LnrS7o",
    "url": "https://www.youtube.com/watch?v=e3OV3LnrS7o",
    "country": "US",
    "popularity_metrics": {
      "views": 336991,
      "likes": 8618,
      "comments": 322,
      "like_to_view_ratio": 0.025573,
      "comment_to_view_ratio": 0.000956
    }
  },
  {
    "workflow": "STOP Wasting Time & Master n8n AI Agents in 11 Minutes",
    "platform": "YouTube",
    "source_id": "ZQFE8rdel3E",
    "url": "https://www.youtube.com/watch?v=ZQFE8rdel3E",
    "country": "US",
    "popularity_metrics": {
      "views": 25075,
      "likes": 0,
      "comments": 15,
      "like_to_view_ratio": 0.0,
      "comment_to_view_ratio": 0.000598
    }
  },
  {
    "workflow": "n8n's AI Workflow Builder is out - how to enable and use it",
    "platform": "YouTube",
    "source_id": "zTTRz9RN9v4",
    "url": "https://www.youtube.com/watch?v=zTTRz9RN9v4",
    "country": "US",
    "popularity_metrics": {
      "views": 14180,
      "likes": 344,
      "comments": 81,
      "like_to_view_ratio": 0.02426,
      "comment_to_view_ratio": 0.005712
    }
  },
  {
    "workflow": "n8n will change your life as a developer...",
    "platform": "YouTube",
    "source_id": "bS9R6aCVEzw",
    "url": "https://www.youtube.com/watch?v=bS9R6aCVEzw",
    "country": "US",
    "popularity_metrics": {
      "views": 1035109,
      "likes": 52061,
      "comments": 1937,
      "like_to_view_ratio": 0.050295,
      "comment_to_view_ratio": 0.001871
    }
  },
  {
    "workflow": "n8n Masterclass: Build AI Agents & Automate Workflows (Beginner to Pro)",
    "platform": "YouTube",
    "source_id": "ZHH3sr234zY",
    "url": "https://www.youtube.com/watch?v=ZHH3sr234zY",
    "country": "US",
    "popularity_metrics": {
      "views": 449245,
      "likes": 12338,
      "comments": 379,
      "like_to_view_ratio": 0.027464,
      "comment_to_view_ratio": 0.000844
    }
  },
  {
    "workflow": "n8n Tutorial for Beginners - Build Your First Free AI Agent",
    "platform": "YouTube",
    "source_id": "dpoMEcXjVH8",
    "url": "https://www.youtube.com/watch?v=dpoMEcXjVH8",
    "country": "US",
    "popularity_metrics": {
      "views": 224378,
      "likes": 4439,
      "comments": 166,
      "like_to_view_ratio": 0.019784,
      "comment_to_view_ratio": 0.00074
    }
  },
  {
    "workflow": "Can n8n's AI Workflow Builder Make Workflows Better Than Me?",
    "platform": "YouTube",
    "source_id": "a43jFW5U834",
    "url": "https://www.youtube.com/watch?v=a43jFW5U834",
    "country": "US",
    "popularity_metrics": {
      "views": 1114,
      "likes": 17,
      "comments": 1,
      "like_to_view_ratio": 0.01526,
      "comment_to_view_ratio": 0.000898
    }
  },
  {
    "workflow": "1000+ n8n Workflows Just Got Leaked — Start Here",
    "platform": "YouTube",
    "source_id": "udcS8fHi-j0",
    "url": "https://www.youtube.com/watch?v=udcS8fHi-j0",
    "country": "US",
    "popularity_metrics": {
      "views": 24685,
      "likes": 546,
      "comments": 295,
      "like_to_view_ratio": 0.022119,
      "comment_to_view_ratio": 0.011951
    }
  },
  {
    "workflow": "How Developers Build n8n Workflows (Made Simple) #techtok #automation #n8n",
    "platform": "YouTube",
    "source_id": "D_oWThznAuc",
    "url": "https://www.youtube.com/watch?v=D_oWThznAuc",
    "country": "US",
    "popularity_metrics": {
      "views": 4611,
      "likes": 241,
      "comments": 9,
      "like_to_view_ratio": 0.052266,
      "comment_to_view_ratio": 0.001952
    }
  },
  {
    "workflow": "5 Error Handling Techniques for Production n8n Workflows",
    "platform": "YouTube",
    "source_id": "Zy4cVtHJNvc",
    "url": "https://www.youtube.com/watch?v=Zy4cVtHJNvc",
    "country": "US",
    "popularity_metrics": {
      "views": 28770,
      "likes": 1529,
      "comments": 10,
      "like_to_view_ratio": 0.053146,
      "comment_to_view_ratio": 0.000348
    }
  },
  {
    "workflow": "You NEED to Use n8n RIGHT NOW!! (Free, Local, Private)",
    "platform": "YouTube",
    "source_id": "ONgECvZNI3o",
    "url": "https://www.youtube.com/watch?v=ONgECvZNI3o",
    "country": "US",
    "popularity_metrics": {
      "views": 2237981,
      "likes": 89138,
      "comments": 2447,
      "like_to_view_ratio": 0.03983,
      "comment_to_view_ratio": 0.001093
    }
  },
  {
    "workflow": "the n8n killer? AGENTIC WORKFLOWS: Full Beginner's Guide",
    "platform": "YouTube",
    "source_id": "bA-WmidVSGo",
    "url": "https://www.youtube.com/watch?v=bA-WmidVSGo",
    "country": "US",
    "popularity_metrics": {
      "views": 98065,
      "likes": 3500,
      "comments": 375,
      "like_to_view_ratio": 0.035691,
      "comment_to_view_ratio": 0.003824
    }
  },
  {
    "workflow": "Cool Automation with n8n",
    "platform": "YouTube",
    "source_id": "Fd9Fi9zQ7Qc",
    "url": "https://www.youtube.com/watch?v=Fd9Fi9zQ7Qc",
    "country": "US",
    "popularity_metrics": {
      "views": 187654,
      "likes": 3637,
      "comments": 41,
      "like_to_view_ratio": 0.019381,
      "comment_to_view_ratio": 0.000218
    }
  },
  {
    "workflow": "This n8n AI Agent Will Manage Your Email Inbox (100% Automatic)",
    "platform": "YouTube",
    "source_id": "l0SiFihbetA",
    "url": "https://www.youtube.com/watch?v=l0SiFihbetA",
    "country": "US",
    "popularity_metrics": {
      "views": 64857,
      "likes": 1019,
      "comments": 85,
      "like_to_view_ratio": 0.015711,
      "comment_to_view_ratio": 0.001311
    }
  },
  {
    "workflow": "Set up Google Credentials in n8n in 5 minutes (2025)",
    "platform": "YouTube",
    "source_id": "3Ai1EPznlAc",
    "url": "https://www.youtube.com/watch?v=3Ai1EPznlAc",
    "country": "US",
    "popularity_metrics": {
      "views": 219731,
      "likes": 4101,
      "comments": 286,
      "like_to_view_ratio": 0.018664,
      "comment_to_view_ratio": 0.001302
    }
  },
  {
    "workflow": "How To Connect Gmail To n8n - Step by Step",
    "platform": "YouTube",
    "source_id": "tSM8NYUKXP4",
    "url": "https://www.youtube.com/watch?v=tSM8NYUKXP4",
    "country": "US",
    "popularity_metrics": {
      "views": 13015,
      "likes": 120,
      "comments": 15,
      "like_to_view_ratio": 0.00922,
      "comment_to_view_ratio": 0.001153
    }
  },
  {
    "workflow": "How I Built an AI Agent to Automate my Emails in n8n (Step by Step, No Code)",
    "platform": "YouTube",
    "source_id": "KIJHRq_Tg6o",
    "url": "https://www.youtube.com/watch?v=KIJHRq_Tg6o",
    "country": "US",
    "popularity_metrics": {
      "views": 90467,
      "likes": 1573,
      "comments": 78,
      "like_to_view_ratio": 0.017388,
      "comment_to_view_ratio": 0.000862
    }
  },
  {
    "workflow": "I Built an Ultimate Gmail AI Agent with No Code (free n8n template)",
    "platform": "YouTube",
    "source_id": "IRGXJXhLa_s",
    "url": "https://www.youtube.com/watch?v=IRGXJXhLa_s",
    "country": "US",
    "popularity_metrics": {
      "views": 1000,
      "likes": 26,
      "comments": 6,
      "like_to_view_ratio": 0.026,
      "comment_to_view_ratio": 0.006
    }
  },
  {
    "workflow": "How to Connect Google Services to n8n (Step-by-Step Tutorial)",
    "platform": "YouTube",
    "source_id": "988BIzIkhcw",
    "url": "https://www.youtube.com/watch?v=988BIzIkhcw",
    "country": "US",
    "popularity_metrics": {
      "views": 5641,
      "likes": 167,
      "comments": 19,
      "like_to_view_ratio": 0.029605,
      "comment_to_view_ratio": 0.003368
    }
  },
  {
    "workflow": "Gmail on Autopilot: 15 Insane n8n Automation Hacks",
    "platform": "YouTube",
    "source_id": "_2bfCG9922E",
    "url": "https://www.youtube.com/watch?v=_2bfCG9922E",
    "country": "US",
    "popularity_metrics": {
      "views": 18830,
      "likes": 358,
      "comments": 29,
      "like_to_view_ratio": 0.019012,
      "comment_to_view_ratio": 0.00154
    }
  },
  {
    "workflow": "Connect Gmail with n8n – Simple 2025 Setup Guide",
    "platform": "YouTube",
    "source_id": "v-PD0novMJ8",
    "url": "https://www.youtube.com/watch?v=v-PD0novMJ8",
    "country": "US",
    "popularity_metrics": {
      "views": 10057,
      "likes": 132,
      "comments": 39,
      "like_to_view_ratio": 0.013125,
      "comment_to_view_ratio": 0.003878
    }
  },
  {
    "workflow": "I Upgraded My Gmail AI Agent (n8n beginner guide, free template)",
    "platform": "YouTube",
    "source_id": "z5Om-Jd_r1M",
    "url": "https://www.youtube.com/watch?v=z5Om-Jd_r1M",
    "country": "US",
    "popularity_metrics": {
      "views": 2505,
      "likes": 49,
      "comments": 9,
      "like_to_view_ratio": 0.019561,
      "comment_to_view_ratio": 0.003593
    }
  },
  {
    "workflow": "Tutoriel n8n & Google 2025 : Connecter Gmail, Drive et Sheets, Calendar, Docs",
    "platform": "YouTube",
    "source_id": "95ThtuSXKtM",
    "url": "https://www.youtube.com/watch?v=95ThtuSXKtM",
    "country": "US",
    "popularity_metrics": {
      "views": 658,
      "likes": 20,
      "comments": 11,
      "like_to_view_ratio": 0.030395,
      "comment_to_view_ratio": 0.016717
    }
  },
  {
    "workflow": "This Gmail AI Agent classifies/labels incoming Emails and even generates a personal response #n8n",
    "platform": "YouTube",
    "source_id": "hxvvl9g7_Zg",
    "url": "https://www.youtube.com/watch?v=hxvvl9g7_Zg",
    "country": "US",
    "popularity_metrics": {
      "views": 28587,
      "likes": 1067,
      "comments": 28,
      "like_to_view_ratio": 0.037325,
      "comment_to_view_ratio": 0.000979
    }
  },
  {
    "workflow": "Build an AI Email Assistant in n8n | Gmail Automation Walkthrough",
    "platform": "YouTube",
    "source_id": "fNBHxZtNPiY",
    "url": "https://www.youtube.com/watch?v=fNBHxZtNPiY",
    "country": "US",
    "popularity_metrics": {
      "views": 6540,
      "likes": 104,
      "comments": 32,
      "like_to_view_ratio": 0.015902,
      "comment_to_view_ratio": 0.004893
    }
  },
  {
    "workflow": "I Built an AI Agent to Manage my Gmail (free n8n template, no code)",
    "platform": "YouTube",
    "source_id": "iISKXAv_97k",
    "url": "https://www.youtube.com/watch?v=iISKXAv_97k",
    "country": "US",
    "popularity_metrics": {
      "views": 6170,
      "likes": 120,
      "comments": 17,
      "like_to_view_ratio": 0.019449,
      "comment_to_view_ratio": 0.002755
    }
  },
  {
    "workflow": "Build an AI Agent That Reads & Replies to Gmail (No Code)",
    "platform": "YouTube",
    "source_id": "ZcP4BwY9rHw",
    "url": "https://www.youtube.com/watch?v=ZcP4BwY9rHw",
    "country": "US",
    "popularity_metrics": {
      "views": 46434,
      "likes": 352,
      "comments": 12,
      "like_to_view_ratio": 0.007581,
      "comment_to_view_ratio": 0.000258
    }
  },
  {
    "workflow": "How to connect N8N to Gmail, Google Sheets, Drive, Docs, Calendar (Google Auth)",
    "platform": "YouTube",
    "source_id": "0GX7xEeRPIo",
    "url": "https://www.youtube.com/watch?v=0GX7xEeRPIo",
    "country": "US",
    "popularity_metrics": {
      "views": 5330,
      "likes": 146,
      "comments": 10,
      "like_to_view_ratio": 0.027392,
      "comment_to_view_ratio": 0.001876
    }
  },
  {
    "workflow": "How To Build an Email Agent in Under a Minute with n8n  #n8n #agentgpt #artificialintelligence",
    "platform": "YouTube",
    "source_id": "PwdayYM_hkU",
    "url": "https://www.youtube.com/watch?v=PwdayYM_hkU",
    "country": "US",
    "popularity_metrics": {
      "views": 66986,
      "likes": 1980,
      "comments": 39,
      "like_to_view_ratio": 0.029558,
      "comment_to_view_ratio": 0.000582
    }
  },
  {
    "workflow": "How to CONNECT Gmail to n8n (Step by Step) 2025",
    "platform": "YouTube",
    "source_id": "SBPU5a8-8Xo",
    "url": "https://www.youtube.com/watch?v=SBPU5a8-8Xo",
    "country": "US",
    "popularity_metrics": {
      "views": 18172,
      "likes": 331,
      "comments": 38,
      "like_to_view_ratio": 0.018215,
      "comment_to_view_ratio": 0.002091
    }
  },
  {
    "workflow": "n8n Automation Made Simple: Gmail + AI Agent Setup",
    "platform": "YouTube",
    "source_id": "HrczDh6tWog",
    "url": "https://www.youtube.com/watch?v=HrczDh6tWog",
    "country": "US",
    "popularity_metrics": {
      "views": 108,
      "likes": 5,
      "comments": 0,
      "like_to_view_ratio": 0.046296,
      "comment_to_view_ratio": 0.0
    }
  },
  {
    "workflow": "n8n Google Credentials Setup (2025) | Connect to Sheets, Drive & Gmail Fast",
    "platform": "YouTube",
    "source_id": "CbDvca7sHl0",
    "url": "https://www.youtube.com/watch?v=CbDvca7sHl0",
    "country": "US",
    "popularity_metrics": {
      "views": 642,
      "likes": 14,
      "comments": 8,
      "like_to_view_ratio": 0.021807,
      "comment_to_view_ratio": 0.012461
    }
  },
  {
    "workflow": "Build an AI Gmail Assistant Agent with N8N - Complete Step-by-Step Tutorial | Email Automation",
    "platform": "YouTube",
    "source_id": "qRTKTWYhubM",
    "url": "https://www.youtube.com/watch?v=qRTKTWYhubM",
    "country": "US",
    "popularity_metrics": {
      "views": 496,
      "likes": 12,
      "comments": 1,
      "like_to_view_ratio": 0.024194,
      "comment_to_view_ratio": 0.002016
    }
  },
  {
    "workflow": "Setup Google Credentials in n8n in 5 Minutes (Google Sheets, Drive, & Gmail)",
    "platform": "YouTube",
    "source_id": "lXNIteL16Z0",
    "url": "https://www.youtube.com/watch?v=lXNIteL16Z0",
    "country": "US",
    "popularity_metrics": {
      "views": 13044,
      "likes": 516,
      "comments": 75,
      "like_to_view_ratio": 0.039558,
      "comment_to_view_ratio": 0.00575
    }
  },
  {
    "workflow": "Build a Gmail Inbox Manager in n8n (no code, step-by-step)",
    "platform": "YouTube",
    "source_id": "ydnwSPbOsq4",
    "url": "https://www.youtube.com/watch?v=ydnwSPbOsq4",
    "country": "US",
    "popularity_metrics": {
      "views": 3708,
      "likes": 68,
      "comments": 12,
      "like_to_view_ratio": 0.018339,
      "comment_to_view_ratio": 0.003236
    }
  },
  {
    "workflow": "I Built an Inbox AI Agent That Handles Your Emails (No-Code, n8n)",
    "platform": "YouTube",
    "source_id": "cHFKgOmr6rY",
    "url": "https://www.youtube.com/watch?v=cHFKgOmr6rY",
    "country": "US",
    "popularity_metrics": {
      "views": 8706,
      "likes": 267,
      "comments": 91,
      "like_to_view_ratio": 0.030669,
      "comment_to_view_ratio": 0.010453
    }
  },
  {
    "workflow": "Set Up Google Credentials In n8n In 5 Mins (Gmail, Drive, Sheets & More)",
    "platform": "YouTube",
    "source_id": "H1Kt1adcr84",
    "url": "https://www.youtube.com/watch?v=H1Kt1adcr84",
    "country": "US",
    "popularity_metrics": {
      "views": 52000,
      "likes": 1457,
      "comments": 181,
      "like_to_view_ratio": 0.028019,
      "comment_to_view_ratio": 0.003481
    }
  },
  {
    "workflow": "Build an AI Email Agent in n8n with Gmail—No Code Needed! Automate Emails Fast! #n8n #nocode",
    "platform": "YouTube",
    "source_id": "_ZYV2Fknovw",
    "url": "https://www.youtube.com/watch?v=_ZYV2Fknovw",
    "country": "US",
    "popularity_metrics": {
      "views": 6275,
      "likes": 88,
      "comments": 1,
      "like_to_view_ratio": 0.014024,
      "comment_to_view_ratio": 0.000159
    }
  },
  {
    "workflow": ":mega: We Need Your Help! (Answer & Earn)",
    "platform": "Forum",
    "source_id": "80361",
    "url": "https://community.n8n.io/t/we-need-your-help-answer-earn/80361",
    "country": "GLOBAL",
    "popularity_metrics": {
      "views": 51160,
      "likes": 761,
      "replies": 125,
      "unique_contributors": 0,
      "engagement_score": 886
    }
  },
  {
    "workflow": "Welcome to the n8n Community!",
    "platform": "Forum",
    "source_id": "7",
    "url": "https://community.n8n.io/t/welcome-to-the-n8n-community/7",
    "country": "GLOBAL",
    "popularity_metrics": {
      "views": 16149,
      "likes": 81,
      "replies": 0,
      "unique_contributors": 0,
      "engagement_score": 81
    }
  },
  {
    "workflow": "After upgrading n8n Docker (1.106 → 1.120.1), workflows reverted and ~2 weeks of changes disappeared (SQLite)",
    "platform": "Forum",
    "source_id": "244081",
    "url": "https://community.n8n.io/t/after-upgrading-n8n-docker-1-106-1-120-1-workflows-reverted-and-2-weeks-of-changes-disappeared-sqlite/244081",
    "country": "GLOBAL",
    "popularity_metrics": {
      "views": 6,
      "likes": 0,
      "replies": 0,
      "unique_contributors": 0,
      "engagement_score": 0
    }
  },
  {
    "workflow": "The ui is really nice",
    "platform": "Forum",
    "source_id": "244083",
    "url": "https://community.n8n.io/t/the-ui-is-really-nice/244083",
    "country": "GLOBAL",
    "popularity_metrics": {
      "views": 2,
      "likes": 0,
      "replies": 0,
      "unique_contributors": 0,
      "engagement_score": 0
    }
  },
  {
    "workflow": "Social Network",
    "platform": "Forum",
    "source_id": "244078",
    "url": "https://community.n8n.io/t/social-network/244078",
    "country": "GLOBAL",
    "popularity_metrics": {
      "views": 2,
      "likes": 0,
      "replies": 0,
      "unique_contributors": 0,
      "engagement_score": 0
    }
  },
  {
    "workflow": "How to convert string into n8n json workflow compatible?",
    "platform": "Forum",
    "source_id": "244067",
    "url": "https://community.n8n.io/t/how-to-convert-string-into-n8n-json-workflow-compatible/244067",
    "country": "GLOBAL",
    "popularity_metrics": {
      "views": 5,
      "likes": 0,
      "replies": 0,
      "unique_contributors": 0,
      "engagement_score": 0
    }
  },
  {
    "workflow": "Instagram Automation gives a bad request with a 400 error with valid API",
    "platform": "Forum",
    "source_id": "243518",
    "url": "https://community.n8n.io/t/instagram-automation-gives-a-bad-request-with-a-400-error-with-valid-api/243518",
    "country": "GLOBAL",
    "popularity_metrics": {
      "views": 37,
      "likes": 4,
      "replies": 5,
      "unique_contributors": 0,
      "engagement_score": 9
    }
  },
  {
    "workflow": "Sort Node — drag to reorder fields",
    "platform": "Forum",
    "source_id": "244058",
    "url": "https://community.n8n.io/t/sort-node-drag-to-reorder-fields/244058",
    "country": "GLOBAL",
    "popularity_metrics": {
      "views": 6,
      "likes": 0,
      "replies": 0,
      "unique_contributors": 0,
      "engagement_score": 0
    }
  },
  {
    "workflow": "WhatsApp Business Cloud node is not working",
    "platform": "Forum",
    "source_id": "244059",
    "url": "https://community.n8n.io/t/whatsapp-business-cloud-node-is-not-working/244059",
    "country": "GLOBAL",
    "popularity_metrics": {
      "views": 6,
      "likes": 0,
      "replies": 0,
      "unique_contributors": 0,
      "engagement_score": 0
    }
  },
  {
    "workflow": "WhatsApp Business Cloud node \"on message\" is not working",
    "platform": "Forum",
    "source_id": "244054",
    "url": "https://community.n8n.io/t/whatsapp-business-cloud-node-on-message-is-not-working/244054",
    "country": "GLOBAL",
    "popularity_metrics": {
      "views": 5,
      "likes": 0,
      "replies": 0,
      "unique_contributors": 0,
      "engagement_score": 0
    }
  },
  {
    "workflow": "Level 1 badge to add to Li profile",
    "platform": "Forum",
    "source_id": "244000",
    "url": "https://community.n8n.io/t/level-1-badge-to-add-to-li-profile/244000",
    "country": "GLOBAL",
    "popularity_metrics": {
      "views": 21,
      "likes": 0,
      "replies": 0,
      "unique_contributors": 0,
      "engagement_score": 0
    }
  },
  {
    "workflow": "Values become undefined",
    "platform": "Forum",
    "source_id": "237737",
    "url": "https://community.n8n.io/t/values-become-undefined/237737",
    "country": "GLOBAL",
    "popularity_metrics": {
      "views": 81,
      "likes": 3,
      "replies": 0,
      "unique_contributors": 0,
      "engagement_score": 3
    }
  },
  {
    "workflow": "OAuth Redirect URL Missing HTTPS Protocol",
    "platform": "Forum",
    "source_id": "244013",
    "url": "https://community.n8n.io/t/oauth-redirect-url-missing-https-protocol/244013",
    "country": "GLOBAL",
    "popularity_metrics": {
      "views": 10,
      "likes": 0,
      "replies": 0,
      "unique_contributors": 0,
      "engagement_score": 0
    }
  },
  {
    "workflow": "Hey, I'm only getting 77% at the theory and 89% at the practical part of the level 1 course. is this a bug? It also says there are only 13 questions but I have to answer 16",
    "platform": "Forum",
    "source_id": "244009",
    "url": "https://community.n8n.io/t/hey-im-only-getting-77-at-the-theory-and-89-at-the-practical-part-of-the-level-1-course-is-this-a-bug-it-also-says-there-are-only-13-questions-but-i-have-to-answer-16/244009",
    "country": "GLOBAL",
    "popularity_metrics": {
      "views": 10,
      "likes": 0,
      "replies": 0,
      "unique_contributors": 0,
      "engagement_score": 0
    }
  },
  {
    "workflow": "CALDAV calendar options",
    "platform": "Forum",
    "source_id": "10141",
    "url": "https://community.n8n.io/t/caldav-calendar-options/10141",
    "country": "GLOBAL",
    "popularity_metrics": {
      "views": 8303,
      "likes": 46,
      "replies": 17,
      "unique_contributors": 0,
      "engagement_score": 63
    }
  },
  {
    "workflow": "Can't seem to save a file locally",
    "platform": "Forum",
    "source_id": "243356",
    "url": "https://community.n8n.io/t/cant-seem-to-save-a-file-locally/243356",
    "country": "GLOBAL",
    "popularity_metrics": {
      "views": 26,
      "likes": 1,
      "replies": 0,
      "unique_contributors": 0,
      "engagement_score": 1
    }
  },
  {
    "workflow": "Estoy aprendidndo como comunicarme estees mi priner contacto es correcto?",
    "platform": "Forum",
    "source_id": "243979",
    "url": "https://community.n8n.io/t/estoy-aprendidndo-como-comunicarme-estees-mi-priner-contacto-es-correcto/243979",
    "country": "GLOBAL",
    "popularity_metrics": {
      "views": 8,
      "likes": 1,
      "replies": 0,
      "unique_contributors": 0,
      "engagement_score": 1
    }
  },
  {
    "workflow": "Community Node - QR Code Generator",
    "platform": "Forum",
    "source_id": "243974",
    "url": "https://community.n8n.io/t/community-node-qr-code-generator/243974",
    "country": "GLOBAL",
    "popularity_metrics": {
      "views": 7,
      "likes": 0,
      "replies": 0,
      "unique_contributors": 0,
      "engagement_score": 0
    }
  },
  {
    "workflow": "Excel node not working?",
    "platform": "Forum",
    "source_id": "243307",
    "url": "https://community.n8n.io/t/excel-node-not-working/243307",
    "country": "GLOBAL",
    "popularity_metrics": {
      "views": 56,
      "likes": 0,
      "replies": 9,
      "unique_contributors": 0,
      "engagement_score": 9
    }
  },
  {
    "workflow": "Self hosted 2.x",
    "platform": "Forum",
    "source_id": "243966",
    "url": "https://community.n8n.io/t/self-hosted-2-x/243966",
    "country": "GLOBAL",
    "popularity_metrics": {
      "views": 14,
      "likes": 0,
      "replies": 0,
      "unique_contributors": 0,
      "engagement_score": 0
    }
  },
  {
    "workflow": "Trial hosted account -- Cannot execute ANY steps, even the most basic ... \"Connection Lost to Server\"",
    "platform": "Forum",
    "source_id": "243221",
    "url": "https://community.n8n.io/t/trial-hosted-account-cannot-execute-any-steps-even-the-most-basic-connection-lost-to-server/243221",
    "country": "GLOBAL",
    "popularity_metrics": {
      "views": 38,
      "likes": 0,
      "replies": 4,
      "unique_contributors": 0,
      "engagement_score": 4
    }
  },
  {
    "workflow": "Everytime I save or Publish it duplicates",
    "platform": "Forum",
    "source_id": "243958",
    "url": "https://community.n8n.io/t/everytime-i-save-or-publish-it-duplicates/243958",
    "country": "GLOBAL",
    "popularity_metrics": {
      "views": 9,
      "likes": 0,
      "replies": 0,
      "unique_contributors": 0,
      "engagement_score": 0
    }
  },
  {
    "workflow": "My n8n node is stuck in manual review for 2 months",
    "platform": "Forum",
    "source_id": "243258",
    "url": "https://community.n8n.io/t/my-n8n-node-is-stuck-in-manual-review-for-2-months/243258",
    "country": "GLOBAL",
    "popularity_metrics": {
      "views": 34,
      "likes": 0,
      "replies": 3,
      "unique_contributors": 0,
      "engagement_score": 3
    }
  },
  {
    "workflow": "Slack Trigger (Events API) can’t verify Request URL: “Your request URL responded with an HTTP error / didn’t respond with challenge”",
    "platform": "Forum",
    "source_id": "243947",
    "url": "https://community.n8n.io/t/slack-trigger-events-api-can-t-verify-request-url-your-request-url-responded-with-an-http-error-didn-t-respond-with-challenge/243947",
    "country": "GLOBAL",
    "popularity_metrics": {
      "views": 6,
      "likes": 0,
      "replies": 0,
      "unique_contributors": 0,
      "engagement_score": 0
    }
  },
  {
    "workflow": "Apify Issue",
    "platform": "Forum",
    "source_id": "243185",
    "url": "https://community.n8n.io/t/apify-issue/243185",
    "country": "GLOBAL",
    "popularity_metrics": {
      "views": 46,
      "likes": 6,
      "replies": 7,
      "unique_contributors": 0,
      "engagement_score": 13
    }
  },
  {
    "workflow": "Help with workflow",
    "platform": "Forum",
    "source_id": "239050",
    "url": "https://community.n8n.io/t/help-with-workflow/239050",
    "country": "GLOBAL",
    "popularity_metrics": {
      "views": 36,
      "likes": 0,
      "replies": 1,
      "unique_contributors": 0,
      "engagement_score": 1
    }
  },
  {
    "workflow": "N8N Cloud Instance Inaccessible",
    "platform": "Forum",
    "source_id": "243862",
    "url": "https://community.n8n.io/t/n8n-cloud-instance-inaccessible/243862",
    "country": "GLOBAL",
    "popularity_metrics": {
      "views": 19,
      "likes": 0,
      "replies": 1,
      "unique_contributors": 0,
      "engagement_score": 1
    }
  },
  {
    "workflow": "Hola estoy perdido necesito ayuda",
    "platform": "Forum",
    "source_id": "243914",
    "url": "https://community.n8n.io/t/hola-estoy-perdido-necesito-ayuda/243914",
    "country": "GLOBAL",
    "popularity_metrics": {
      "views": 8,
      "likes": 2,
      "replies": 0,
      "unique_contributors": 0,
      "engagement_score": 2
    }
  },
  {
    "workflow": "N8N Code Node wants Python 3 installed on the system. I have it, but n8n does not see it",
    "platform": "Forum",
    "source_id": "241912",
    "url": "https://community.n8n.io/t/n8n-code-node-wants-python-3-installed-on-the-system-i-have-it-but-n8n-does-not-see-it/241912",
    "country": "GLOBAL",
    "popularity_metrics": {
      "views": 431,
      "likes": 1,
      "replies": 6,
      "unique_contributors": 0,
      "engagement_score": 7
    }
  },
  {
    "workflow": "Happy New Year to the n8n community! 🎉",
    "platform": "Forum",
    "source_id": "243888",
    "url": "https://community.n8n.io/t/happy-new-year-to-the-n8n-community/243888",
    "country": "GLOBAL",
    "popularity_metrics": {
      "views": 15,
      "likes": 0,
      "replies": 0,
      "unique_contributors": 0,
      "engagement_score": 0
    }
  },
  {
    "workflow": "Our n8n node review process just stuck for almost 3 months how to resolve?",
    "platform": "Forum",
    "source_id": "243938",
    "url": "https://community.n8n.io/t/our-n8n-node-review-process-just-stuck-for-almost-3-months-how-to-resolve/243938",
    "country": "GLOBAL",
    "popularity_metrics": {
      "views": 11,
      "likes": 0,
      "replies": 0,
      "unique_contributors": 0,
      "engagement_score": 0
    }
  },
  {
    "workflow": "N8N Community Node stuck in Manual 'under review' step for over 3 weeks",
    "platform": "Forum",
    "source_id": "219305",
    "url": "https://community.n8n.io/t/n8n-community-node-stuck-in-manual-under-review-step-for-over-3-weeks/219305",
    "country": "GLOBAL",
    "popularity_metrics": {
      "views": 42,
      "likes": 0,
      "replies": 0,
      "unique_contributors": 0,
      "engagement_score": 0
    }
  },
  {
    "workflow": "WhatsApp Trigger stuck on -waiting for you to creat an event in whatsapp",
    "platform": "Forum",
    "source_id": "243930",
    "url": "https://community.n8n.io/t/whatsapp-trigger-stuck-on-waiting-for-you-to-creat-an-event-in-whatsapp/243930",
    "country": "GLOBAL",
    "popularity_metrics": {
      "views": 12,
      "likes": 0,
      "replies": 0,
      "unique_contributors": 0,
      "engagement_score": 0
    }
  },
  {
    "workflow": "I need help 😫",
    "platform": "Forum",
    "source_id": "243842",
    "url": "https://community.n8n.io/t/i-need-help/243842",
    "country": "GLOBAL",
    "popularity_metrics": {
      "views": 19,
      "likes": 5,
      "replies": 4,
      "unique_contributors": 0,
      "engagement_score": 9
    }
  },
  {
    "workflow": "Dynamic mapping of a JavaScript (JSON) Object to a HTTP `searchParams` (n8n `query`)",
    "platform": "Forum",
    "source_id": "239365",
    "url": "https://community.n8n.io/t/dynamic-mapping-of-a-javascript-json-object-to-a-http-searchparams-n8n-query/239365",
    "country": "GLOBAL",
    "popularity_metrics": {
      "views": 33,
      "likes": 0,
      "replies": 1,
      "unique_contributors": 0,
      "engagement_score": 1
    }
  },
  {
    "workflow": "N8N locally and google",
    "platform": "Forum",
    "source_id": "243317",
    "url": "https://community.n8n.io/t/n8n-locally-and-google/243317",
    "country": "GLOBAL",
    "popularity_metrics": {
      "views": 68,
      "likes": 2,
      "replies": 5,
      "unique_contributors": 0,
      "engagement_score": 7
    }
  },
  {
    "workflow": "Microsoft Teams Trigger - Trigger stops listening shortly after new subscription has been made",
    "platform": "Forum",
    "source_id": "242510",
    "url": "https://community.n8n.io/t/microsoft-teams-trigger-trigger-stops-listening-shortly-after-new-subscription-has-been-made/242510",
    "country": "GLOBAL",
    "popularity_metrics": {
      "views": 33,
      "likes": 1,
      "replies": 1,
      "unique_contributors": 0,
      "engagement_score": 2
    }
  },
  {
    "workflow": "Workflow Not Firing",
    "platform": "Forum",
    "source_id": "243904",
    "url": "https://community.n8n.io/t/workflow-not-firing/243904",
    "country": "GLOBAL",
    "popularity_metrics": {
      "views": 10,
      "likes": 0,
      "replies": 0,
      "unique_contributors": 0,
      "engagement_score": 0
    }
  },
  {
    "workflow": "N8n version 1.109.2 image or pod compatibility with cgroups v2 upon cgroups v1 removal before openshift migration to 4.19",
    "platform": "Forum",
    "source_id": "240272",
    "url": "https://community.n8n.io/t/n8n-version-1-109-2-image-or-pod-compatibility-with-cgroups-v2-upon-cgroups-v1-removal-before-openshift-migration-to-4-19/240272",
    "country": "GLOBAL",
    "popularity_metrics": {
      "views": 25,
      "likes": 0,
      "replies": 0,
      "unique_contributors": 0,
      "engagement_score": 0
    }
  },
  {
    "workflow": "Happy New Year to the entire n8n community! 🎉",
    "platform": "Forum",
    "source_id": "243886",
    "url": "https://community.n8n.io/t/happy-new-year-to-the-entire-n8n-community/243886",
    "country": "GLOBAL",
    "popularity_metrics": {
      "views": 10,
      "likes": 0,
      "replies": 0,
      "unique_contributors": 0,
      "engagement_score": 0
    }
  },
  {
    "workflow": "Is there a way to control or specify the “About” description text shown on my n8n integration page, or is it added by the n8n team?",
    "platform": "Forum",
    "source_id": "243087",
    "url": "https://community.n8n.io/t/is-there-a-way-to-control-or-specify-the-about-description-text-shown-on-my-n8n-integration-page-or-is-it-added-by-the-n8n-team/243087",
    "country": "GLOBAL",
    "popularity_metrics": {
      "views": 27,
      "likes": 0,
      "replies": 0,
      "unique_contributors": 0,
      "engagement_score": 0
    }
  },
  {
    "workflow": "Why i see this in my selfhosted log",
    "platform": "Forum",
    "source_id": "243870",
    "url": "https://community.n8n.io/t/why-i-see-this-in-my-selfhosted-log/243870",
    "country": "GLOBAL",
    "popularity_metrics": {
      "views": 17,
      "likes": 0,
      "replies": 0,
      "unique_contributors": 0,
      "engagement_score": 0
    }
  },
  {
    "workflow": "OAuth2 stopped working after several weeks reliable running",
    "platform": "Forum",
    "source_id": "239616",
    "url": "https://community.n8n.io/t/oauth2-stopped-working-after-several-weeks-reliable-running/239616",
    "country": "GLOBAL",
    "popularity_metrics": {
      "views": 49,
      "likes": 0,
      "replies": 2,
      "unique_contributors": 0,
      "engagement_score": 2
    }
  },
  {
    "workflow": "Unknown error in Code node",
    "platform": "Forum",
    "source_id": "243619",
    "url": "https://community.n8n.io/t/unknown-error-in-code-node/243619",
    "country": "GLOBAL",
    "popularity_metrics": {
      "views": 45,
      "likes": 1,
      "replies": 9,
      "unique_contributors": 0,
      "engagement_score": 10
    }
  },
  {
    "workflow": "Level 1 Course Badge - Completed but Not Received",
    "platform": "Forum",
    "source_id": "240054",
    "url": "https://community.n8n.io/t/level-1-course-badge-completed-but-not-received/240054",
    "country": "GLOBAL",
    "popularity_metrics": {
      "views": 44,
      "likes": 4,
      "replies": 3,
      "unique_contributors": 0,
      "engagement_score": 7
    }
  },
  {
    "workflow": "Issues with Call n8n Workflow tool",
    "platform": "Forum",
    "source_id": "238744",
    "url": "https://community.n8n.io/t/issues-with-call-n8n-workflow-tool/238744",
    "country": "GLOBAL",
    "popularity_metrics": {
      "views": 112,
      "likes": 1,
      "replies": 4,
      "unique_contributors": 0,
      "engagement_score": 5
    }
  },
  {
    "workflow": "N8n Cloud: Executions stuck in “Queued / Starting soon” for hours while “No active executions” is shown",
    "platform": "Forum",
    "source_id": "242425",
    "url": "https://community.n8n.io/t/n8n-cloud-executions-stuck-in-queued-starting-soon-for-hours-while-no-active-executions-is-shown/242425",
    "country": "GLOBAL",
    "popularity_metrics": {
      "views": 48,
      "likes": 1,
      "replies": 4,
      "unique_contributors": 0,
      "engagement_score": 5
    }
  },
  {
    "workflow": "In n8n Version 2.1.4 the active workflow button doesn't exist?",
    "platform": "Forum",
    "source_id": "243790",
    "url": "https://community.n8n.io/t/in-n8n-version-2-1-4-the-active-workflow-button-doesnt-exist/243790",
    "country": "GLOBAL",
    "popularity_metrics": {
      "views": 28,
      "likes": 2,
      "replies": 1,
      "unique_contributors": 0,
      "engagement_score": 3
    }
  },
  {
    "workflow": "Unable to execute any workflows in testing (and production fails)",
    "platform": "Forum",
    "source_id": "243097",
    "url": "https://community.n8n.io/t/unable-to-execute-any-workflows-in-testing-and-production-fails/243097",
    "country": "GLOBAL",
    "popularity_metrics": {
      "views": 55,
      "likes": 0,
      "replies": 1,
      "unique_contributors": 0,
      "engagement_score": 1
    }
  },
  {
    "workflow": "Webhook production url only working in test",
    "platform": "Forum",
    "source_id": "80228",
    "url": "https://community.n8n.io/t/webhook-production-url-only-working-in-test/80228",
    "country": "GLOBAL",
    "popularity_metrics": {
      "views": 2292,
      "likes": 12,
      "replies": 5,
      "unique_contributors": 0,
      "engagement_score": 17
    }
  },
  {
    "workflow": "n8n workflow",
    "platform": "Google",
    "source_id": "n8n workflow",
    "url": "",
    "country": "US",
    "popularity_metrics": {
      "trend_values": [
        32,
        27,
        27,
        35,
        39,
        29,
        36,
        26,
        25,
        20
      ],
      "start_value": 88,
      "end_value": 20,
      "trend_percentage_change": -77.27
    }
  },
  {
    "workflow": "n8n automation",
    "platform": "Google",
    "source_id": "n8n automation",
    "url": "",
    "country": "US",
    "popularity_metrics": {
      "trend_values": [
        22,
        18,
        20,
        27,
        28,
        25,
        24,
        22,
        16,
        16
      ],
      "start_value": 71,
      "end_value": 16,
      "trend_percentage_change": -77.46
    }
  },
  {
    "workflow": "n8n gmail",
    "platform": "Google",
    "source_id": "n8n gmail",
    "url": "",
    "country": "US",
    "popularity_metrics": {
      "trend_values": [
        13,
        11,
        14,
        13,
        12,
        16,
        15,
        8,
        8,
        0
      ],
      "start_value": 0,
      "end_value": 0,
      "trend_percentage_change": 0
    }
  },
  {
    "workflow": "n8n webhook",
    "platform": "Google",
    "source_id": "n8n webhook",
    "url": "",
    "country": "US",
    "popularity_metrics": {
      "trend_values": [
        24,
        17,
        18,
        24,
        25,
        23,
        24,
        17,
        11,
        18
      ],
      "start_value": 0,
      "end_value": 18,
      "trend_percentage_change": 0
    }
  },
  {
    "workflow": "n8n slack",
    "platform": "Google",
    "source_id": "n8n slack",
    "url": "",
    "country": "US",
    "popularity_metrics": {
      "trend_values": [
        11,
        0,
        5,
        9,
        8,
        0,
        9,
        6,
        5,
        0
      ],
      "start_value": 0,
      "end_value": 0,
      "trend_percentage_change": 0
    }
  },
  {
    "workflow": "n8n whatsapp",
    "platform": "Google",
    "source_id": "n8n whatsapp",
    "url": "",
    "country": "US",
    "popularity_metrics": {
      "trend_values": [
        14,
        9,
        14,
        16,
        14,
        14,
        19,
        8,
        5,
        0
      ],
      "start_value": 0,
      "end_value": 0,
      "trend_percentage_change": 0
    }
  },
  {
    "workflow": "n8n airtable",
    "platform": "Google",
    "source_id": "n8n airtable",
    "url": "",
    "country": "US",
    "popularity_metrics": {
      "trend_values": [
        67,
        0,
        0,
        0,
        0,
        100,
        54,
        0,
        60,
        0
      ],
      "start_value": 0,
      "end_value": 0,
      "trend_percentage_change": 0
    }
  },
  {
    "workflow": "n8n google sheets",
    "platform": "Google",
    "source_id": "n8n google sheets",
    "url": "",
    "country": "US",
    "popularity_metrics": {
      "trend_values": [
        15,
        8,
        8,
        13,
        13,
        10,
        15,
        9,
        5,
        0
      ],
      "start_value": 0,
      "end_value": 0,
      "trend_percentage_change": 0
    }
  },
  {
    "workflow": "n8n integration",
    "platform": "Google",
    "source_id": "n8n integration",
    "url": "",
    "country": "US",
    "popularity_metrics": {
      "trend_values": [
        21,
        14,
        17,
        20,
        25,
        18,
        18,
        15,
        12,
        11
      ],
      "start_value": 48,
      "end_value": 11,
      "trend_percentage_change": -77.08
    }
  },
  {
    "workflow": "n8n cron",
    "platform": "Google",
    "source_id": "n8n cron",
    "url": "",
    "country": "US",
    "popularity_metrics": {
      "trend_values": [
        0,
        0,
        0,
        0,
        0,
        100,
        0,
        0,
        0,
        0
      ],
      "start_value": 0,
      "end_value": 0,
      "trend_percentage_change": 0
    }
  },
  {
    "workflow": "n8n tutorial",
    "platform": "Google",
    "source_id": "n8n tutorial",
    "url": "",
    "country": "US",
    "popularity_metrics": {
      "trend_values": [
        10,
        10,
        8,
        16,
        15,
        14,
        15,
        7,
        6,
        0
      ],
      "start_value": 0,
      "end_value": 0,
      "trend_percentage_change": 0
    }
  }
]